adext/__init__.py
adext/adext.py
adext-0.4.7.dist-info/licenses/LICENSE
adext-0.4.7.dist-info/METADATA
adext-0.4.7.dist-info/WHEEL
adext-0.4.7.dist-info/top_level.txt
adext-0.4.7.dist-info/RECORD
