Metadata-Version: 2.4
Name: adext
Version: 0.4.7
Summary: AlarmDecoder extended
Home-page: https://github.com/ajschmidt8/adext
Author: AJ Schmidt
License: MIT
Classifier: Development Status :: 5 - Production/Stable
Classifier: License :: OSI Approved :: MIT License
Classifier: Programming Language :: Python :: 3.4
Classifier: Topic :: Software Development :: Libraries :: Python Modules
Classifier: Topic :: Communications
Classifier: Topic :: Home Automation
Classifier: Topic :: Security
License-File: LICENSE
Requires-Dist: alarmdecoder==1.13.14
Dynamic: author
Dynamic: classifier
Dynamic: description
Dynamic: description-content-type
Dynamic: home-page
Dynamic: license
Dynamic: license-file
Dynamic: requires-dist
Dynamic: summary
